wisefood/__init__.py
wisefood/api_client.py
wisefood/autocomplete.py
wisefood/client.py
wisefood/exceptions.py
wisefood/entities/articles.py
wisefood/entities/base.py
wisefood/entities/fctables.py
wisefood/entities/guides.py
wisefood/entities/households.py
wisefood-0.0.8.dist-info/licenses/LICENSE
wisefood-0.0.8.dist-info/METADATA
wisefood-0.0.8.dist-info/WHEEL
wisefood-0.0.8.dist-info/top_level.txt
wisefood-0.0.8.dist-info/RECORD
