Metadata-Version: 2.4
Name: wisefood
Version: 0.0.8
Summary: A small client for accessing and managing resources in the WiseFood platform.
Author-email: dpetrou <dpetrou@athenarc.gr>
License:                                  Apache License
Project-URL: Homepage, https://github.com/wisefood/wisefood-client
Project-URL: Issues, https://github.com/wisefood/wisefood-client/issues
Requires-Python: >=3.8
License-File: LICENSE
Requires-Dist: requests>=2.28
Dynamic: license-file
